{"ProjectBreakpoints":"{\"Value\":{\"Lookup WE05 and Ariba Report.xaml\":[{\"ConditionalExpression\":null,\"ActionExpression\":null,\"ExpectedHitCounter\":null,\"ShouldContinueAfterAction\":false,\"BreakpointType\":1,\"LocationIdentifier\":\"Assign\",\"IsEnabled\":true,\"Annotation\":null,\"Id\":\"d3933ffe-d49e-4b56-b737-16654a9e3799\",\"ActivityIdRef\":\"Assign_1\",\"ActivityId\":\"1.52\",\"ActivityName\":\"Assign\",\"IsTransient\":false}]},\"CodeBreakpoints\":{}}","OpenedDocuments":"[{\"DocumentPath\":\"Main.xaml\",\"FactoryId\":\"{ACB8E7BA-F093-44C1-9B50-33ECA51AAE16}\"},{\"DocumentPath\":\"Excel workflows/Lookup WE05 file and Ariba SAP  file.xaml\",\"FactoryId\":\"{ACB8E7BA-F093-44C1-9B50-33ECA51AAE16}\"},{\"DocumentPath\":\"Lookup WE05 and Ariba Report.xaml\",\"FactoryId\":\"{ACB8E7BA-F093-44C1-9B50-33ECA51AAE16}\"},{\"DocumentPath\":\"Upload Queue Item.xaml\",\"FactoryId\":\"{ACB8E7BA-F093-44C1-9B50-33ECA51AAE16}\"}]","ProjectActivitiesViewState":"{\"Lookup WE05 and Ariba Report.xaml\":[{\"ActivityIdRef\":\"AddDataColumn`1_1\",\"IsAdvancedOptionsExpanded\":false,\"Widgets\":{}},{\"ActivityIdRef\":\"ForEachRow_1\",\"IsAdvancedOptionsExpanded\":false,\"Categories\":{\"\":true},\"Widgets\":{\"Body\":{\"ShowExpanded\":true}}},{\"ActivityIdRef\":\"Read_Excel_as_Database_1\",\"IsAdvancedOptionsExpanded\":false,\"Widgets\":{}},{\"ActivityIdRef\":\"ForEachRow_2\",\"IsAdvancedOptionsExpanded\":false,\"Categories\":{\"\":true},\"Widgets\":{\"Body\":{\"ShowExpanded\":true}}},{\"ActivityIdRef\":\"LookupDataTable_1\",\"IsAdvancedOptionsExpanded\":false,\"Widgets\":{}},{\"ActivityIdRef\":\"If_1\",\"IsAdvancedOptionsExpanded\":false,\"Widgets\":{}}],\"Upload Queue Item.xaml\":[{\"ActivityIdRef\":\"AddQueueItem_1\",\"IsAdvancedOptionsExpanded\":false,\"Categories\":{\"Input\":true,\"Misc\":true},\"Widgets\":{}},{\"ActivityIdRef\":\"Read_Excel_as_Database_1\",\"IsAdvancedOptionsExpanded\":false,\"Widgets\":{}}]}","Compiler":"2","ProjectWatches":"{\"Value\":[]}"}